data_point_client/__init__.py
data_point_client/api/__init__.py
data_point_client/api/data_export/__init__.py
data_point_client/api/data_export/data_export_create_csv_export.py
data_point_client/api/data_point/__init__.py
data_point_client/api/data_point/data_point_append_execution_result_data.py
data_point_client/api/data_point/data_point_append_time_series_data.py
data_point_client/api/data_point/data_point_create_data_point.py
data_point_client/api/data_point/data_point_delete_data_point.py
data_point_client/api/data_point/data_point_delete_data_point_cleanup_rule.py
data_point_client/api/data_point/data_point_finish_execution_result_data.py
data_point_client/api/data_point/data_point_get_data.py
data_point_client/api/data_point/data_point_get_data_point.py
data_point_client/api/data_point/data_point_get_data_point_by_version.py
data_point_client/api/data_point/data_point_get_data_points.py
data_point_client/api/data_point/data_point_get_data_quality.py
data_point_client/api/data_point/data_point_get_quality_statistic.py
data_point_client/api/data_point/data_point_get_value_over_time.py
data_point_client/api/data_point/data_point_update_constant_data.py
data_point_client/api/data_point/data_point_update_data_point.py
data_point_client/api/data_point/data_point_update_data_point_cleanup_rule.py
data_point_client/api/data_point/data_point_update_data_point_unit.py
data_point_client/api/data_point/data_point_update_day_period_data.py
data_point_client/api/data_point/data_point_update_time_series_data.py
data_point_client/api/data_point/data_point_update_week_period_data.py
data_point_client/api/data_point_area/__init__.py
data_point_client/api/data_point_area/data_point_area_create_area.py
data_point_client/api/data_point_area/data_point_area_create_area_message.py
data_point_client/api/data_point_area/data_point_area_delete_area.py
data_point_client/api/data_point_area/data_point_area_delete_message.py
nista_library-6.6.0.dist-info/LICENSE.md
nista_library-6.6.0.dist-info/METADATA
nista_library-6.6.0.dist-info/WHEEL
nista_library-6.6.0.dist-info/RECORD
