Metadata-Version: 2.3
Name: nista-library
Version: 6.6.0
Summary: A client library for accessing nista.io
License: MIT
Author: Markus Pichler
Author-email: markus.pichler@nista.io
Requires-Python: >=3.9,<4.0
Classifier: License :: OSI Approved :: MIT License
Classifier: Programming Language :: Python :: 3
Classifier: Programming Language :: Python :: 3.9
Classifier: Programming Language :: Python :: 3.10
Classifier: Programming Language :: Python :: 3.11
Classifier: Programming Language :: Python :: 3.12
Classifier: Programming Language :: Python :: 3.13
Requires-Dist: PyJWT (>=2.3.0,<3.0.0)
Requires-Dist: attrs (>=20.1.0,<25.0.0)
Requires-Dist: colorama (>=0.4.4,<0.5.0)
Requires-Dist: httpx (>=0.15.4,<1.0.0)
Requires-Dist: keyring (>=24.0.0,<25.0.0)
Requires-Dist: oauth2-client (>=1.2.1,<2.0.0)
Requires-Dist: pandas (>=1.3.2)
Requires-Dist: pyjwt (>=2.6.0,<3.0.0)
Requires-Dist: python-dateutil (>=2.8.0,<3.0.0)
Requires-Dist: structlog (>=21.0.0,<26.0.0)
Project-URL: Homepage, https://nista.io
Project-URL: Repository, https://gitlab.com/campfiresolutions/public/nista.io-python-library.git
